Jupyterchatzz/__init__.py
Jupyterchatzz/_version.py
jupyterchatzz-0.2.6.data/data/share/jupyter/labextensions/Jupyterchatzz/package.json
jupyterchatzz-0.2.6.data/data/share/jupyter/labextensions/Jupyterchatzz/static/index.js
jupyterchatzz-0.2.6.data/data/share/jupyter/labextensions/Jupyterchatzz/static/package.json
jupyterchatzz-0.2.6.data/data/share/jupyter/labextensions/Jupyterchatzz/static/style.js
jupyterchatzz-0.2.6.data/data/share/jupyter/labextensions/Jupyterchatzz/install.json
jupyterchatzz-0.2.6.dist-info/METADATA
jupyterchatzz-0.2.6.dist-info/WHEEL
jupyterchatzz-0.2.6.dist-info/licenses/LICENSE
jupyterchatzz-0.2.6.dist-info/RECORD
