Metadata-Version: 2.4
Name: Jupyterchatzz
Version: 0.2.6
Dynamic: Keywords
Summary: A JupyterLab extension.
Project-URL: Homepage, https://github.com/Zhoums/Jupyterchatzz
Project-URL: Bug Tracker, https://github.com/Zhoums/Jupyterchatzz/issues
Project-URL: Repository, https://github.com/Zhoums/Jupyterchatzz.git
Author-email: Zhoums <18652950852@163.com>
License: BSD 3-Clause License
License-File: LICENSE
Classifier: Framework :: Jupyter
Classifier: Framework :: Jupyter :: JupyterLab
Classifier: Framework :: Jupyter :: JupyterLab :: 4
Classifier: Framework :: Jupyter :: JupyterLab :: Extensions
Classifier: Framework :: Jupyter :: JupyterLab :: Extensions :: Prebuilt
Classifier: License :: OSI Approved :: BSD License
Classifier: Programming Language :: Python
Classifier: Programming Language :: Python :: 3
Classifier: Programming Language :: Python :: 3.8
Classifier: Programming Language :: Python :: 3.9
Classifier: Programming Language :: Python :: 3.10
Classifier: Programming Language :: Python :: 3.11
Requires-Python: >=3.8
Requires-Dist: ipython>=8.0.0
Requires-Dist: jupyter-mcp-server>=0.1.0
Requires-Dist: jupyter>=1.0.0
Requires-Dist: jupyterlab<5,>=4.0.0
